{
  "job_id": "JD011",
  "job_title": "Machine Learning Engineer",
  "company": "AILabs",
  "job_description": "Company: AILabs\nPosition: Machine Learning Engineer\nLocation: Palo Alto, CA (Hybrid)\nSalary: $150,000 - $250,000\n\nAbout Us:\nAILabs is at the forefront of AI research and development, focused on creating cutting-edge solutions. We are passionate about solving complex problems with data.\n\nJob Description:\nWe are seeking a Machine Learning Engineer to research, develop, and deploy machine learning models. The ideal candidate will have a strong background in machine learning algorithms and software engineering.\n\nResponsibilities:\n- Research and develop machine learning models.\n- Implement and deploy machine learning models in production.\n- Evaluate model performance and iterate on improvements.\n- Collaborate with data scientists and engineers.\n\nRequirements:\n- Master's or PhD in Computer Science, Statistics, or related field.\n- 3+ years of experience in machine learning.\n- Proficient in Python and machine learning libraries (e.g., TensorFlow, PyTorch, scikit-learn).\n- Experience with cloud computing platforms.\n\nPreferred Qualifications:\n- Publications in machine learning conferences.\n- Experience with deep learning.\n- Knowledge of MLOps principles.\n\nBenefits:\n- Competitive salary and benefits package.\n- Opportunity to work on cutting-edge AI research.\n- Collaborative and supportive work environment.",
  "required_skills": [
    "Python",
    "TensorFlow",
    "PyTorch",
    "scikit-learn",
    "MLOps",
    "Data Modeling"
  ],
  "preferred_skills": [
    "Deep Learning",
    "AWS",
    "Kubeflow"
  ],
  "min_experience": 3,
  "education_requirement": "Master's",
  "job_category": "Data",
  "location": "Palo Alto, CA (Hybrid)",
  "salary_range": "$150,000 - $250,000"
}