{
  "job_id": "JD013",
  "job_title": "AI Research Engineer",
  "company": "FrontierTech",
  "job_description": "Company: FrontierTech\nPosition: AI Research Engineer\nLocation: Palo Alto, CA (On-site)\nSalary: $160,000 - $220,000\n\nAbout Us:\nFrontierTech is an AI research company pushing the boundaries of artificial intelligence. We are dedicated to innovation and developing groundbreaking AI technologies.\n\nJob Description:\nWe are seeking a highly skilled AI Research Engineer to conduct research and develop new AI algorithms and models. The ideal candidate will have a strong background in machine learning and deep learning.\n\nResponsibilities:\n- Conduct research on new AI algorithms and models.\n- Implement and evaluate AI models using TensorFlow or PyTorch.\n- Publish research papers in top AI conferences.\n- Collaborate with other researchers and engineers.\n\nRequirements:\n- PhD in Computer Science or a related field.\n- Strong background in machine learning and deep learning.\n- Proficiency in Python and machine learning frameworks like TensorFlow or PyTorch.\n- Publications in top AI conferences.\n\nPreferred Qualifications:\n- Experience with natural language processing (NLP).\n- Experience with computer vision.\n- Experience with reinforcement learning.\n\nBenefits:\n- Opportunity to work on cutting-edge AI research.\n- Competitive salary and benefits package.\n- Collaborative and intellectually stimulating environment.",
  "required_skills": [
    "Python",
    "TensorFlow",
    "PyTorch",
    "Machine Learning",
    "Deep Learning",
    "AI Research",
    "Data Science"
  ],
  "preferred_skills": [
    "NLP",
    "Computer Vision",
    "Reinforcement Learning"
  ],
  "min_experience": 0,
  "education_requirement": "PhD",
  "job_category": "Data",
  "location": "Palo Alto, CA (On-site)",
  "salary_range": "$160,000 - $220,000"
}