{
  "job_id": "JD002",
  "job_title": "Data Scientist",
  "company": "AnalyticsHub",
  "job_description": "Company: AnalyticsHub\nPosition: Data Scientist\nLocation: Remote\nSalary: $130,000 - $170,000\n\nAbout Us:\nAnalyticsHub is a leading provider of data-driven solutions. We empower businesses to make informed decisions using cutting-edge analytics techniques. We are comprised of passionate data professionals.\n\nJob Description:\nWe are seeking a talented Data Scientist to join our growing team. The ideal candidate will have a strong background in statistical modeling, machine learning, and data visualization.\n\nResponsibilities:\n- Develop and implement machine learning models to solve business problems.\n- Perform data analysis and generate insights using statistical techniques.\n- Build data visualizations and dashboards to communicate findings to stakeholders.\n- Collaborate with cross-functional teams to identify and address data-related challenges.\n\nRequirements:\n- Master's degree in Statistics, Mathematics, Computer Science, or related field.\n- 3+ years of experience in data science or related field.\n- Proficiency in Python and data science libraries (e.g., Pandas, NumPy, scikit-learn).\n- Experience with machine learning algorithms (e.g., regression, classification, clustering).\n\nPreferred Qualifications:\n- Experience with cloud computing platforms (e.g., AWS, Azure, GCP).\n- Knowledge of deep learning frameworks (e.g., TensorFlow, PyTorch).\n- Experience with big data technologies (e.g., Spark, Hadoop).\n\nBenefits:\n- Competitive salary and benefits package.\n- Opportunity to work on challenging and impactful projects.\n- Remote work environment.\n- Professional development opportunities.",
  "required_skills": [
    "Python",
    "Pandas",
    "NumPy",
    "scikit-learn",
    "SQL"
  ],
  "preferred_skills": [
    "TensorFlow",
    "PyTorch",
    "AWS"
  ],
  "min_experience": 3,
  "education_requirement": "Master's",
  "job_category": "Data",
  "location": "Remote",
  "salary_range": "$130,000 - $170,000"
}