{
  "job_id": "JD-001",
  "job_title": "Frontend Software Engineer",
  "company": "WebFront",
  "job_description": "Company: WebFront\nPosition: Frontend Software Engineer\nLocation: San Francisco, CA (Hybrid)\nSalary: $120,000 - $150,000\n\nAbout Us:\nWebFront is a leading provider of user-friendly web applications and progressive web apps. We focus on creating the best user experiences through innovation and exceptional UI design. We value creativity, collaboration, and continuous learning.\n\nJob Description:\nWe are looking for a Frontend Software Engineer to join our team. You will be responsible for developing and maintaining the user interface of our web applications. The ideal candidate will have excellent JavaScript skills and experience with modern frameworks like React.\n\nResponsibilities:\n- Develop new user-facing features using React.js\n- Build reusable components and front-end libraries for future use\n- Translate designs and wireframes into high-quality code\n- Optimize components for maximum performance across a vast array of web-browsers and devices\n\nRequirements:\n- Bachelor's degree in Computer Science or related field\n- 3+ years of experience in frontend development\n- Proficient in JavaScript, HTML, and CSS\n- Experience with React.js and Redux\n\nPreferred Qualifications:\n- Experience with Typescript\n- Familiarity with responsive design principles\n- Experience with unit and integration testing\n\nBenefits:\n- Competitive salary and benefits package\n- Opportunity to work on cutting-edge technologies\n- Collaborative and supportive work environment",
  "required_skills": [
    "JavaScript",
    "React",
    "HTML5",
    "CSS3",
    "Git"
  ],
  "preferred_skills": [
    "TypeScript",
    "Redux",
    "SASS"
  ],
  "min_experience": 3,
  "education_requirement": "Bachelor's",
  "job_category": "Frontend",
  "location": "San Francisco, CA (Hybrid)",
  "salary_range": "$120,000 - $150,000"
}