{
  "job_id": "JD015",
  "job_title": "UI/UX Developer",
  "company": "WebFront",
  "job_description": "Company: WebFront\nPosition: UI/UX Developer\nLocation: Remote\nSalary: $95,000 - $135,000\n\nAbout Us:\nWebFront is a leading provider of innovative web solutions. We are passionate about creating engaging and user-friendly experiences. We value collaboration and continuous learning.\n\nJob Description:\nWe are looking for a UI/UX Developer to join our dynamic team. The ideal candidate will have a strong understanding of user-centered design principles and a passion for creating intuitive and visually appealing interfaces.\n\nResponsibilities:\n- Design and develop user interfaces for web and mobile applications.\n- Conduct user research and usability testing.\n- Create wireframes, mockups, and prototypes.\n- Collaborate with developers and product managers to implement designs.\n\nRequirements:\n- 2+ years of experience in UI/UX design and development.\n- Strong proficiency in HTML, CSS, JavaScript, and UI design tools like Figma or Adobe XD.\n- Understanding of user-centered design principles.\n- Experience with responsive design and cross-browser compatibility.\n\nPreferred Qualifications:\n- Experience with React or Angular.\n- Portfolio of past UI/UX projects.\n- Strong communication and presentation skills.\n\nBenefits:\n- Competitive salary and benefits package.\n- Opportunity to work on cutting-edge technologies.\n- Collaborative and supportive work environment.",
  "required_skills": [
    "HTML5",
    "CSS3",
    "JavaScript",
    "UI Design",
    "UX Design",
    "Figma",
    "Adobe XD"
  ],
  "preferred_skills": [
    "React",
    "Angular",
    "User Research"
  ],
  "min_experience": 2,
  "education_requirement": "Bachelor's",
  "job_category": "Frontend",
  "location": "Remote",
  "salary_range": "$95,000 - $135,000"
}