{
  "job_id": "JD-004",
  "job_title": "Data Scientist",
  "company": "AILabs",
  "job_description": "Company: AILabs\nPosition: Data Scientist\nLocation: Mountain View, CA (Hybrid)\nSalary: $150,000 - $180,000\n\nAbout Us:\nAILabs is a leading artificial intelligence research and development company. We are committed to pushing the boundaries of AI and developing innovative solutions to real-world problems.\n\nJob Description:\nWe are looking for a Data Scientist to join our team. You will be responsible for developing and deploying machine learning models. The ideal candidate will have experience with Python, scikit-learn, and TensorFlow.\n\nResponsibilities:\n- Develop and deploy machine learning models\n- Analyze large datasets to identify trends and insights\n- Communicate findings to stakeholders\n- Collaborate with engineers and product managers\n\nRequirements:\n- Master's degree in Computer Science, Statistics, or related field\n- 3+ years of experience in data science\n- Proficient in Python\n- Experience with scikit-learn and TensorFlow\n\nPreferred Qualifications:\n- Experience with PyTorch\n- Experience with cloud platforms (AWS, Azure, GCP)\n- Experience with data visualization tools (Tableau, Power BI)\n\nBenefits:\n- Competitive salary and benefits package\n- Opportunity to work on cutting-edge research\n- Collaborative and supportive work environment",
  "required_skills": [
    "Python",
    "scikit-learn",
    "TensorFlow",
    "Pandas",
    "NumPy",
    "SQL"
  ],
  "preferred_skills": [
    "PyTorch",
    "Tableau"
  ],
  "min_experience": 3,
  "education_requirement": "Master's",
  "job_category": "Data",
  "location": "Mountain View, CA (Hybrid)",
  "salary_range": "$150,000 - $180,000"
}