{
  "job_id": "JD-009",
  "job_title": "Technical Project Manager",
  "company": "NextGenSystems",
  "job_description": "Company: NextGenSystems\nPosition: Technical Project Manager\nLocation: Dallas, TX (Hybrid)\nSalary: $130,000 - $160,000\n\nAbout Us:\nNextGenSystems delivers innovative technology solutions to help businesses thrive in the digital age. We are committed to excellence and customer satisfaction.\n\nJob Description:\nWe are looking for a Technical Project Manager to lead cross-functional teams and deliver complex software projects on time and within budget. You will be responsible for planning, executing, and monitoring project progress.\n\nResponsibilities:\n- Define project scope, goals, and deliverables\n- Develop project plans and timelines\n- Manage project budgets and resources\n- Track project progress and report on status\n- Identify and mitigate project risks\n\nRequirements:\n- Bachelor's degree in Computer Science or related field\n- 5+ years of experience in project management\n- Strong understanding of software development methodologies\n- Excellent communication and interpersonal skills\n\nPreferred Qualifications:\n- PMP certification\n- Agile experience\n\nBenefits:\n- Competitive salary and benefits package\n- Opportunity to work on challenging and rewarding projects\n- Collaborative and supportive work environment",
  "required_skills": [
    "Project Management",
    "Agile",
    "Scrum",
    "Communication",
    "Risk Management",
    "Stakeholder Management"
  ],
  "preferred_skills": [
    "PMP",
    "Jira"
  ],
  "min_experience": 5,
  "education_requirement": "Bachelor's",
  "job_category": "Management",
  "location": "Dallas, TX (Hybrid)",
  "salary_range": "$130,000 - $160,000"
}