{
  "job_id": "JD015",
  "job_title": "UI/UX Developer",
  "company": "WebFront",
  "job_description": "Company: WebFront\nPosition: UI/UX Developer\nLocation: San Francisco, CA (Hybrid)\nSalary: $110,000 - $140,000\n\nAbout Us:\nWebFront is a leading provider of cutting-edge web solutions. We are passionate about creating intuitive and innovative user experiences.\n\nJob Description:\nWe are seeking a UI/UX Developer to design and develop user interfaces for our web applications. The ideal candidate will have experience with HTML, CSS, JavaScript, and UI/UX design principles.\n\nResponsibilities:\n- Design and develop user interfaces.\n- Conduct user research and usability testing.\n- Create wireframes and prototypes.\n- Collaborate with developers and product managers.\n\nRequirements:\n- Bachelor's degree in Design or related field.\n- 3+ years of experience in UI/UX development.\n- Proficiency in HTML, CSS, and JavaScript.\n- Experience with UI/UX design tools (e.g., Figma, Adobe XD).\n\nPreferred Qualifications:\n- Experience with React or Angular.\n- Knowledge of accessibility standards.\n- Portfolio of UI/UX design projects.\n\nBenefits:\n- Competitive salary and benefits package.\n- Opportunity to work on challenging and rewarding projects.\n- Collaborative and supportive work environment.",
  "required_skills": [
    "HTML5",
    "CSS3",
    "JavaScript",
    "UI Design",
    "UX Design",
    "Wireframing"
  ],
  "preferred_skills": [
    "React",
    "Figma"
  ],
  "min_experience": 3,
  "education_requirement": "Bachelor's",
  "job_category": "Frontend",
  "location": "San Francisco, CA (Hybrid)",
  "salary_range": "$110,000 - $140,000"
}