{
  "job_id": "JD012",
  "job_title": "Site Reliability Engineer",
  "company": "NextGenSystems",
  "job_description": "Company: NextGenSystems\nPosition: Site Reliability Engineer\nLocation: Seattle, WA\nSalary: $150,000 - $190,000\n\nAbout Us:\nNextGenSystems builds highly reliable and scalable software infrastructure. We provide critical services to millions of users worldwide. We prioritize automation and data-driven decision-making to ensure optimal system performance.\n\nJob Description:\nWe are seeking a skilled Site Reliability Engineer (SRE) to help us maintain and improve the reliability of our systems. You will be responsible for identifying and resolving production issues, automating operational tasks, and improving system monitoring. The ideal candidate will have a strong background in systems administration, software development, and cloud technologies.\n\nResponsibilities:\n- Monitor system performance and identify potential issues.\n- Respond to production incidents and provide timely resolution.\n- Automate operational tasks using scripting languages or configuration management tools.\n- Improve system monitoring and alerting capabilities.\n\nRequirements:\n- Bachelor's degree in Computer Science or related field.\n- 3+ years of experience in systems administration, software development, or SRE.\n- Proficiency in scripting languages (Python, Bash).\n- Experience with cloud platforms (AWS, Azure, or GCP).\n\nPreferred Qualifications:\n- Experience with configuration management tools (Ansible, Chef, or Puppet).\n- Experience with monitoring tools (Prometheus, Grafana).\n- Experience with Kubernetes.\n\nBenefits:\n- Competitive salary and benefits package.\n- Opportunities for professional development.\n- Collaborative and supportive work environment.",
  "required_skills": [
    "Python",
    "Linux",
    "AWS",
    "Docker",
    "Kubernetes",
    "Monitoring",
    "Automation"
  ],
  "preferred_skills": [
    "Ansible",
    "Prometheus",
    "Grafana"
  ],
  "min_experience": 3,
  "education_requirement": "Bachelor's",
  "job_category": "DevOps",
  "location": "Seattle, WA",
  "salary_range": "$150,000 - $190,000"
}