{
  "job_id": "JD003",
  "job_title": "DevOps Engineer",
  "company": "DevSecOps",
  "job_description": "Company: DevSecOps\nPosition: DevOps Engineer\nLocation: New York, NY (On-site)\nSalary: $110,000 - $140,000\n\nAbout Us:\nDevSecOps is a leading provider of DevOps and security solutions. We help organizations automate their software delivery pipelines and improve their security posture.\n\nJob Description:\nWe are looking for a DevOps Engineer to join our team. The ideal candidate will have experience with automating infrastructure and application deployments.\n\nResponsibilities:\n- Automate infrastructure provisioning and configuration using Terraform and Ansible.\n- Implement and maintain CI/CD pipelines using Jenkins and GitHub Actions.\n- Monitor system performance and troubleshoot issues.\n- Collaborate with development and security teams to improve our overall DevOps practices.\n\nRequirements:\n- 2+ years of experience in DevOps or a related role.\n- Experience with cloud platforms like AWS or Azure.\n- Experience with containerization technologies like Docker and Kubernetes.\n- Strong scripting skills in Python or Bash.\n\nPreferred Qualifications:\n- Experience with security tools like SonarQube or Fortify.\n- Experience with monitoring tools like Prometheus or Grafana.\n- AWS Certified DevOps Engineer.\n\nBenefits:\n- Comprehensive health insurance.\n- Stock options.\n- Paid time off for volunteering.",
  "required_skills": [
    "AWS",
    "Docker",
    "Kubernetes",
    "Terraform",
    "Ansible",
    "Jenkins",
    "Git"
  ],
  "preferred_skills": [
    "Prometheus",
    "Grafana"
  ],
  "min_experience": 2,
  "education_requirement": "Bachelor's",
  "job_category": "DevOps",
  "location": "New York, NY (On-site)",
  "salary_range": "$110,000 - $140,000"
}