{
  "job_id": "JD011",
  "job_title": "Software Engineer (Full Stack)",
  "company": "FullStack Inc",
  "job_description": "Company: FullStack Inc\nPosition: Software Engineer (Full Stack)\nLocation: Atlanta, GA (Remote)\nSalary: $110,000 - $150,000\n\nAbout Us:\nFullStack Inc provides comprehensive software solutions. We are a team of talented full-stack developers. We strive to deliver high quality solutions to our customers.\n\nJob Description:\nWe are looking for a Full Stack Software Engineer. The ideal candidate will have experience in both front-end and back-end technologies. You will be proficient with common frameworks and have experience building microservices.\n\nResponsibilities:\n- Develop both front-end and back-end components of web applications.\n- Work with product managers to design and implement new features.\n- Maintain software and troubleshoot customer issues.\n- Participate in code review and improve development processes.\n\nRequirements:\n- Bachelor's degree in Computer Science or related field.\n- 3+ years of experience in software development.\n- Proficiency in JavaScript, HTML, CSS, and a back-end language (e.g., Node.js, Python, Java).\n- Experience with databases (e.g., SQL, MongoDB).\n\nPreferred Qualifications:\n- Experience with React, Angular, or Vue.js.\n- Knowledge of cloud computing platforms (e.g., AWS, Azure, GCP).\n- Familiarity with CI/CD pipelines.\n\nBenefits:\n- Competitive salary and benefits package.\n- Opportunity to work on varied projects.\n- Remote work environment.\n- Professional development opportunities.",
  "required_skills": [
    "JavaScript",
    "HTML5",
    "CSS3",
    "Node.js",
    "SQL"
  ],
  "preferred_skills": [
    "React",
    "AWS"
  ],
  "min_experience": 3,
  "education_requirement": "Bachelor's",
  "job_category": "Full Stack",
  "location": "Atlanta, GA (Remote)",
  "salary_range": "$110,000 - $150,000"
}