{
  "job_id": "JD013",
  "job_title": "Product Manager",
  "company": "FrontierTech",
  "job_description": "Company: FrontierTech\nPosition: Product Manager\nLocation: New York, NY\nSalary: $120,000 - $160,000\n\nAbout Us:\nFrontierTech is developing innovative products. We combine cutting-edge technology. We focus on making our customers leaders in their fields.\n\nJob Description:\nOur product manager will define product vision, strategy, and roadmaps. Interact with customers to gather requirements. Work with engineering on specifications and scheduling.\n\nResponsibilities:\n- Define and communicate product vision and strategy.\n- Gather and prioritize product requirements.\n- Work with engineering to develop product specifications and schedules.\n- Manage the product backlog and prioritize features.\n\nRequirements:\n- Bachelor's degree in Computer Science or related field.\n- 3+ years of experience in product management.\n- Strong analytical and problem-solving skills.\n- Excellent communication and interpersonal skills.\n\nPreferred Qualifications:\n- Experience with Agile development methodologies.\n- Knowledge of software development processes.\n- Technical background.\n\nBenefits:\n- Competitive salary and benefits package.\n- Opportunity to shape the future of our products.\n- Collaborative and supportive work environment.\n- Professional development opportunities.",
  "required_skills": [
    "Agile",
    "Product Management",
    "Communication",
    "Technical Knowledge"
  ],
  "preferred_skills": [
    "Jira",
    "Analytics"
  ],
  "min_experience": 3,
  "education_requirement": "Bachelor's",
  "job_category": "Management",
  "location": "New York, NY",
  "salary_range": "$120,000 - $160,000"
}