{
  "job_id": "JD009",
  "job_title": "Data Engineer",
  "company": "DataFlow",
  "job_description": "Company: DataFlow\nPosition: Data Engineer\nLocation: Boston, MA\nSalary: $120,000 - $160,000\n\nAbout Us:\nDataFlow is a leading provider of data engineering and analytics solutions. We help organizations build and manage their data infrastructure to derive valuable insights.\n\nJob Description:\nWe are looking for a Data Engineer to build and maintain our data pipelines and infrastructure. The ideal candidate will have experience with data warehousing, ETL processes, and big data technologies.\n\nResponsibilities:\n- Design, build, and maintain data pipelines.\n- Develop and optimize ETL processes.\n- Build and manage data warehouses and data lakes.\n- Ensure data quality and reliability.\n\nRequirements:\n- Bachelor's degree in Computer Science or related field.\n- 3+ years of experience in data engineering.\n- Proficiency in SQL and Python.\n- Experience with data warehousing technologies (e.g., Snowflake, Redshift, BigQuery).\n\nPreferred Qualifications:\n- Experience with big data technologies (e.g., Spark, Hadoop).\n- Familiarity with cloud computing platforms (e.g., AWS, Azure, GCP).\n- Knowledge of data governance and security principles.\n\nBenefits:\n- Competitive salary and benefits package.\n- Opportunities for professional development.\n- Collaborative and supportive work environment.",
  "required_skills": [
    "SQL",
    "Python",
    "ETL",
    "Data Warehousing",
    "Spark",
    "AWS"
  ],
  "preferred_skills": [
    "Snowflake",
    "Data Governance",
    "Data Security"
  ],
  "min_experience": 3,
  "education_requirement": "Bachelor's",
  "job_category": "Data",
  "location": "Boston, MA",
  "salary_range": "$120,000 - $160,000"
}