{
  "job_id": "JD002",
  "job_title": "Data Scientist",
  "company": "AILabs",
  "job_description": "Company: AILabs\nPosition: Data Scientist\nLocation: New York, NY\nSalary: $120,000 - $170,000\n\nAbout Us:\nAILabs is at the forefront of artificial intelligence research and development. We are dedicated to pushing the boundaries of what's possible with AI and machine learning.\n\nJob Description:\nWe are seeking an experienced Data Scientist to join our research team. The ideal candidate will have a strong background in statistical modeling, machine learning, and data visualization.\n\nResponsibilities:\n- Develop and implement machine learning models for various applications.\n- Analyze large datasets to identify trends and insights.\n- Communicate findings to technical and non-technical audiences.\n- Collaborate with engineers to deploy models to production.\n\nRequirements:\n- Master's degree in Computer Science, Statistics, or related field.\n- 3+ years of experience in data science.\n- Proficiency in Python and machine learning libraries (scikit-learn, TensorFlow, PyTorch).\n- Experience with data visualization tools like Tableau or Power BI.\n\nPreferred Qualifications:\n- PhD in a related field.\n- Experience with deep learning.\n- Experience with cloud computing platforms (AWS, Azure, GCP).\n\nBenefits:\n- Competitive salary and benefits package.\n- Opportunity to work on cutting-edge research.\n- Collaborative and stimulating work environment.",
  "required_skills": [
    "Python",
    "scikit-learn",
    "TensorFlow",
    "PyTorch",
    "SQL",
    "Pandas"
  ],
  "preferred_skills": [
    "Tableau",
    "Power BI",
    "AWS"
  ],
  "min_experience": 3,
  "education_requirement": "Master's",
  "job_category": "Data",
  "location": "New York, NY",
  "salary_range": "$120,000 - $170,000"
}