{
  "job_id": "JD010",
  "job_title": "AI Research Engineer",
  "company": "AILabs",
  "job_description": "Company: AILabs\nPosition: AI Research Engineer\nLocation: Boston, MA\nSalary: $160,000 - $220,000\n\nAbout Us:\nAILabs is at the forefront of artificial intelligence research and development. We create cutting-edge AI solutions. We are a team of world-class AI researchers.\n\nJob Description:\nWe are seeking an AI Research Engineer to conduct research and develop AI algorithms. The ideal candidate will have a strong background in machine learning, deep learning, and natural language processing.\n\nResponsibilities:\n- Conduct research in machine learning and deep learning.\n- Develop and implement AI algorithms and models.\n- Evaluate and compare the performance of different AI techniques.\n- Publish research papers and present findings at conferences.\n\nRequirements:\n- PhD in Computer Science or related field.\n- 3+ years of experience in AI research.\n- Proficiency in Python and machine learning libraries (e.g., TensorFlow, PyTorch).\n- Strong mathematical and statistical skills.\n\nPreferred Qualifications:\n- Experience with natural language processing.\n- Publications in top AI conferences and journals.\n- Experience with large-scale datasets.\n\nBenefits:\n- Competitive salary and benefits package.\n- Opportunity to work on groundbreaking AI research.\n- Collaborative and supportive research environment.\n- Professional development opportunities.",
  "required_skills": [
    "Python",
    "TensorFlow",
    "PyTorch",
    "Machine Learning",
    "Deep Learning"
  ],
  "preferred_skills": [
    "NLP",
    "R"
  ],
  "min_experience": 3,
  "education_requirement": "PhD",
  "job_category": "Data",
  "location": "Boston, MA",
  "salary_range": "$160,000 - $220,000"
}