{
  "job_id": "JD008",
  "job_title": "Machine Learning Engineer",
  "company": "AILabs",
  "job_description": "Company: AILabs\nPosition: Machine Learning Engineer\nLocation: Mountain View, CA (Hybrid)\nSalary: $160,000 - $200,000\n\nAbout Us:\nAILabs is at the forefront of Artificial Intelligence research and development. We are developing cutting-edge machine learning models for a variety of applications.\n\nJob Description:\nWe are seeking a Machine Learning Engineer with experience in building and deploying ML models. The ideal candidate will be well-versed in TensorFlow, PyTorch and MLOps best practices.\n\nResponsibilities:\n- Design, develop, and deploy machine learning models at scale.\n- Implement MLOps pipelines for continuous training and deployment.\n- Optimize model performance and efficiency.\n- Collaborate with data scientists and engineers.\n\nRequirements:\n- Master's degree in Computer Science or related field.\n- 5+ years of experience in machine learning engineering.\n- Proficiency in Python, TensorFlow, and PyTorch.\n- Experience with cloud platforms (e.g., AWS, Azure, GCP).\n\nPreferred Qualifications:\n- Experience with distributed training frameworks.\n- Experience with model serving technologies (e.g., Kubernetes, SageMaker).\n- Knowledge of ML fairness and ethics.\n\nBenefits:\n- Competitive salary and benefits package.\n- Opportunity to work on innovative AI projects.\n- Research and development budget.",
  "required_skills": [
    "Python",
    "TensorFlow",
    "PyTorch",
    "MLOps",
    "Cloud Platforms",
    "Kubernetes"
  ],
  "preferred_skills": [
    "Model Serving",
    "Distributed Training"
  ],
  "min_experience": 5,
  "education_requirement": "Master's",
  "job_category": "Data",
  "location": "Mountain View, CA (Hybrid)",
  "salary_range": "$160,000 - $200,000"
}