{
  "job_id": "JD009",
  "job_title": "Data Engineer",
  "company": "DataFlow",
  "job_description": "Company: DataFlow\nPosition: Data Engineer\nLocation: Boston, MA (Hybrid)\nSalary: $120,000 - $160,000\n\nAbout Us:\nDataFlow provides cutting-edge data engineering solutions to help businesses unlock the power of their data. We are experts in building scalable and reliable data pipelines. Our team is composed of highly skilled data engineers and architects.\n\nJob Description:\nWe are seeking a talented Data Engineer to join our team. You will be responsible for designing, building, and maintaining data pipelines that ingest, process, and transform data from various sources. The ideal candidate will have a strong background in data warehousing, ETL processing, and cloud technologies.\n\nResponsibilities:\n- Design, build, and maintain data pipelines using tools like Apache Spark, Apache Kafka, or Apache Airflow.\n- Develop and implement data quality checks and validation procedures.\n- Collaborate with data scientists and analysts to ensure data availability and accuracy.\n- Optimize data pipelines for performance and scalability.\n\nRequirements:\n- Bachelor's degree in Computer Science or related field.\n- 3+ years of experience in data engineering.\n- Strong proficiency in SQL and Python.\n- Experience with data warehousing concepts and technologies.\n\nPreferred Qualifications:\n- Experience with cloud platforms (AWS, Azure, or GCP).\n- Experience with NoSQL databases (MongoDB, Cassandra).\n- Experience with data visualization tools (Tableau, Power BI).\n\nBenefits:\n- Competitive salary and benefits package.\n- Opportunities for professional development.\n- Collaborative and supportive work environment.",
  "required_skills": [
    "Python",
    "SQL",
    "AWS",
    "Apache Spark",
    "Apache Kafka",
    "Data Warehousing",
    "ETL"
  ],
  "preferred_skills": [
    "MongoDB",
    "Tableau"
  ],
  "min_experience": 3,
  "education_requirement": "Bachelor's",
  "job_category": "Data",
  "location": "Boston, MA (Hybrid)",
  "salary_range": "$120,000 - $160,000"
}