{
  "job_id": "JD013",
  "job_title": "Database Administrator",
  "company": "DataSystems",
  "job_description": "Company: DataSystems\nPosition: Database Administrator\nLocation: Dallas, TX\nSalary: $110,000 - $140,000\n\nAbout Us:\nDataSystems is a specialist provider of database solutions and services. We manage and optimize databases for some of the world's leading organizations. We are dedicated to delivering reliable, scalable, and secure data solutions.\n\nJob Description:\nWe are seeking a skilled Database Administrator (DBA) to manage and maintain our database infrastructure. You will be responsible for ensuring the availability, performance, and security of our databases. The ideal candidate will have a strong background in database administration, performance tuning, and disaster recovery.\n\nResponsibilities:\n- Install, configure, and maintain database systems (MySQL, PostgreSQL).\n- Monitor database performance and identify areas for improvement.\n- Implement security measures to protect database data.\n- Develop and implement backup and recovery procedures.\n\nRequirements:\n- Bachelor's degree in Computer Science or related field.\n- 3+ years of experience in database administration.\n- Strong proficiency in SQL and database administration tools.\n- Experience with database performance tuning and optimization.\n\nPreferred Qualifications:\n- Experience with cloud-based databases (AWS RDS, Azure SQL Database).\n- Experience with NoSQL databases (MongoDB, Cassandra).\n- Database certifications (Oracle Certified Professional, Microsoft Certified Database Administrator).\n\nBenefits:\n- Competitive salary and benefits package.\n- Opportunities for professional development.\n- Collaborative and supportive work environment.",
  "required_skills": [
    "SQL",
    "MySQL",
    "PostgreSQL",
    "Database Administration",
    "Performance Tuning",
    "Backup and Recovery"
  ],
  "preferred_skills": [
    "AWS RDS",
    "MongoDB"
  ],
  "min_experience": 3,
  "education_requirement": "Bachelor's",
  "job_category": "Backend",
  "location": "Dallas, TX",
  "salary_range": "$110,000 - $140,000"
}