{
  "job_id": "JD007",
  "job_title": "Cloud Architect",
  "company": "CloudScale",
  "job_description": "Company: CloudScale\nPosition: Cloud Architect\nLocation: Chicago, IL\nSalary: $150,000 - $200,000\n\nAbout Us:\nCloudScale helps organizations migrate to the cloud and optimize their cloud infrastructure. We pride ourselves in delivering scalable and cost-effective cloud solutions. We are experts in cloud technologies.\n\nJob Description:\nWe are looking for a Cloud Architect to design and implement cloud-based solutions. The ideal candidate will have experience with cloud architecture, infrastructure automation, and security best practices.\n\nResponsibilities:\n- Design and implement cloud architectures that meet business requirements.\n- Automate infrastructure provisioning and configuration using tools like Terraform and CloudFormation.\n- Ensure security and compliance in cloud environments.\n- Provide technical guidance to development teams.\n\nRequirements:\n- Bachelor's degree in Computer Science or related field.\n- 5+ years of experience in cloud architecture.\n- Proficiency in cloud computing platforms (AWS, Azure, GCP).\n- Experience with infrastructure automation tools.\n\nPreferred Qualifications:\n- Cloud certifications (e.g., AWS Certified Solutions Architect).\n- Knowledge of DevOps principles.\n- Excellent communication and leadership skills.\n\nBenefits:\n- Competitive salary and benefits package.\n- Opportunity to work on complex and impactful cloud projects.\n- Collaborative and supportive work environment.\n- Professional development opportunities.",
  "required_skills": [
    "AWS",
    "Azure",
    "GCP",
    "Terraform",
    "CloudFormation",
    "Kubernetes"
  ],
  "preferred_skills": [
    "Ansible",
    "Python"
  ],
  "min_experience": 5,
  "education_requirement": "Bachelor's",
  "job_category": "DevOps",
  "location": "Chicago, IL",
  "salary_range": "$150,000 - $200,000"
}